mausam/__init__.py
mausam/skeleton.py
mausam-0.1.4.dist-info/LICENSE.txt
mausam-0.1.4.dist-info/METADATA
mausam-0.1.4.dist-info/WHEEL
mausam-0.1.4.dist-info/entry_points.txt
mausam-0.1.4.dist-info/top_level.txt
mausam-0.1.4.dist-info/RECORD
