Metadata-Version: 2.1
Name: mausam
Version: 0.1.4
Summary: An application to upload weather data to IoT dashboards
Home-page: https://github.com/m-anish/mausam/
Author: Anish Mangal
Author-email: anishmg@umich.edu
License: GPL-3.0-or-later
Project-URL: Documentation, https://pyscaffold.org/
Platform: any
Classifier: Development Status :: 4 - Beta
Classifier: Programming Language :: Python
License-File: LICENSE.txt
Requires-Dist: requests
Requires-Dist: simple-youtube-api
Requires-Dist: PyVimeo
Requires-Dist: tinyflux
Requires-Dist: paho-mqtt
Requires-Dist: gpiozero
Requires-Dist: smbus2
Requires-Dist: pillow
Requires-Dist: numpy
Requires-Dist: opencv-python
Requires-Dist: pms7003
Requires-Dist: bme280
Requires-Dist: DateTime
Requires-Dist: tzlocal
Requires-Dist: pytz
Requires-Dist: importlib-metadata ; python_version < "3.8"
Provides-Extra: rpi
Requires-Dist: libcamera ; extra == 'rpi'
Requires-Dist: picamera2 ; extra == 'rpi'
Provides-Extra: testing
Requires-Dist: setuptools ; extra == 'testing'
Requires-Dist: pytest ; extra == 'testing'
Requires-Dist: pytest-cov ; extra == 'testing'
